ptxcompiler/__init__.py
ptxcompiler/_ptxcompilerlib.cpython-312-x86_64-linux-gnu.so
ptxcompiler/_version.py
ptxcompiler/api.py
ptxcompiler/patch.py
ptxcompiler/tests/__init__.py
ptxcompiler/tests/test_lib.py
ptxcompiler/tests/test_patch.py
ptxcompiler_cu11-0.8.1.post3.dist-info/METADATA
ptxcompiler_cu11-0.8.1.post3.dist-info/WHEEL
ptxcompiler_cu11-0.8.1.post3.dist-info/top_level.txt
ptxcompiler_cu11-0.8.1.post3.dist-info/RECORD
ptxcompiler_cu11-0.8.1.post3.dist-info/licenses/LICENSE
