Metadata-Version: 2.4
Name: ptxcompiler-cu11
Version: 0.8.1.post3
Summary: NVIDIA PTX Compiler binding
License: Apache 2.0
License-File: LICENSE
Provides-Extra: test
Requires-Dist: pytest; extra == "test"
Requires-Dist: numba; extra == "test"
Dynamic: license
Dynamic: license-file
Dynamic: provides-extra
Dynamic: summary
